unsendcommunity/__init__.py
unsendcommunity/sdk.py
UnsendCommunity-0.3.2.dist-info/METADATA
UnsendCommunity-0.3.2.dist-info/WHEEL
UnsendCommunity-0.3.2.dist-info/top_level.txt
UnsendCommunity-0.3.2.dist-info/RECORD
