Metadata-Version: 2.1
Name: UnsendCommunity
Version: 0.3.2
Summary: A package for sending and managing emails with the Unsend API
Home-page: UNKNOWN
Author: Harsh Bhat
Author-email: harsh121102@gmail.com
License: UNKNOWN
Platform: UNKNOWN
Classifier: Programming Language :: Python :: 3
Classifier: License :: OSI Approved :: MIT License
Classifier: Operating System :: OS Independent
Requires-Python: >=3.6
Requires-Dist: python-dotenv
Requires-Dist: requests
